parlaycooker/__init__.py
parlaycooker/cli.py
parlaycooker/condition.py
parlaycooker/config.py
parlaycooker/logger.py
parlaycooker/main.py
parlaycooker/model.py
parlaycooker/parlay.py
parlaycooker/read_csv.py
parlaycooker/read_json.py
parlaycooker-0.1.0.dist-info/METADATA
parlaycooker-0.1.0.dist-info/WHEEL
parlaycooker-0.1.0.dist-info/entry_points.txt
parlaycooker-0.1.0.dist-info/top_level.txt
parlaycooker-0.1.0.dist-info/RECORD
