Metadata-Version: 2.4
Name: parlaycooker
Version: 0.1.0
Summary: Add your description here
Requires-Python: >=3.13
Requires-Dist: colorlog>=6.9.0
Requires-Dist: jupyterlab>=4.4.1
Requires-Dist: pandas>=2.2.3
Requires-Dist: pydantic>=2.11.3
Requires-Dist: pytest>=8.3.5
Requires-Dist: pytest-cov>=6.1.1
Requires-Dist: typer>=0.15.3
